PyDeepLX/PyDeepLX.py
PyDeepLX/__init__.py
PyDeepLX-1.0.7.dist-info/LICENSE
PyDeepLX-1.0.7.dist-info/METADATA
PyDeepLX-1.0.7.dist-info/WHEEL
PyDeepLX-1.0.7.dist-info/top_level.txt
PyDeepLX-1.0.7.dist-info/RECORD
